[{"text":"Canvas","link":"#canvas","contents":[{"text":"Monet","link":"https://github.com/rm-hull/monet"},{"text":"Quamolit","link":"https://github.com/Quamolit/quamolit"}]},{"text":"Client/Server Communication","link":"#clientserver-communication","contents":[]},{"text":"Data Serialization","link":"#data-serialization","contents":[{"text":"Cljson","link":"https://github.com/tailrecursion/cljson"},{"text":"Transit","link":"https://github.com/cognitect/transit-cljs"}]},{"text":"Data Visualition","link":"#data-visualition","contents":[{"text":"C2","link":"https://keminglabs.com/c2"}]},{"text":"Database","link":"#database","contents":[{"text":"Datascript","link":"https://github.com/tonsky/datascript"},{"text":"Jaki","link":"https://github.com/pandeiro/jaki"},{"text":"Konserve","link":"https://github.com/replikativ/konserve"}]},{"text":"Development","link":"#development","contents":[{"text":"Ambly","link":"https://github.com/omcljs/ambly"},{"text":"cljs-devtools","link":"https://github.com/binaryage/cljs-devtools"},{"text":"lein-cljsbuild","link":"https://github.com/emezeske/lein-cljsbuild"},{"text":"lein-figwheel","link":"https://github.com/bhauman/lein-figwheel"},{"text":"Ribol","link":"http://docs.caudate.me/ribol/"},{"text":"shadow-build","link":"https://github.com/thheller/shadow-build"}]},{"text":"Document Object Model","link":"#document-object-model","contents":[{"text":"cljs-binding","link":"https://github.com/fluentsoftware/cljs-binding"},{"text":"Crate","link":"https://github.com/ibdknox/crate"},{"text":"Dominator","link":"https://github.com/dubiousdavid/dominator"},{"text":"Dommy","link":"https://github.com/plumatic/dommy"},{"text":"Enfocus","link":"http://ckirkendall.github.io/enfocus-site/"},{"text":"Freactive","link":"https://github.com/aaronc/freactive"},{"text":"Hiccups","link":"https://github.com/teropa/hiccups"},{"text":"Hickory","link":"https://github.com/davidsantiago/hickory"},{"text":"json-html","link":"https://github.com/yogthos/json-html"},{"text":"Kioo","link":"https://github.com/ckirkendall/kioo"},{"text":"Sablono","link":"https://github.com/r0man/sablono"}]},{"text":"Graphics","link":"#graphics","contents":[{"text":"geom","link":"https://github.com/thi-ng/geom"}]},{"text":"HTTP Handler","link":"#http-handler","contents":[{"text":"Castra","link":"https://github.com/hoplon/castra"}]},{"text":"Internationalization","link":"#internationalization","contents":[{"text":"Tower","link":"https://github.com/ptaoussanis/tower"}]},{"text":"JavaScript Interoperability","link":"#javascript-interoperability","contents":[{"text":"CLJSJS","link":"http://cljsjs.github.io/"},{"text":"Jayq","link":"https://github.com/ibdknox/jayq"},{"text":"Purnam","link":"http://purnam.github.io/purnam/"},{"text":"Pylon","link":"https://github.com/bodil/pylon"}]},{"text":"Miscellaneous","link":"#miscellaneous","contents":[{"text":"Automat","link":"https://github.com/ztellman/automat"},{"text":"Bardo","link":"https://github.com/pleasetrythisathome/bardo"},{"text":"core.async","link":"https://github.com/clojure/core.async/"},{"text":"Entanglement","link":"https://github.com/Frozenlock/entanglement"},{"text":"Garden","link":"https://github.com/noprompt/garden"},{"text":"inflections-clj","link":"https://github.com/r0man/inflections-clj"},{"text":"Instaparse","link":"https://github.com/lbradstreet/instaparse-cljs"},{"text":"Keybind","link":"https://github.com/piranha/keybind"},{"text":"markdown-clj","link":"https://github.com/yogthos/markdown-clj"},{"text":"om-tools","link":"https://github.com/plumatic/om-tools"},{"text":"Quil","link":"https://github.com/quil/quil"},{"text":"reforms","link":"https://github.com/bilus/reforms"},{"text":"reagent-forms","link":"https://github.com/reagent-project/reagent-forms/"},{"text":"Respo","link":"https://github.com/mvc-works/respo"},{"text":"Sepal.clj","link":"https://github.com/Cirru/sepal.clj"},{"text":"Truss","link":"https://github.com/ptaoussanis/truss"}]},{"text":"React.js Interface","link":"#reactjs-interface","contents":[]},{"text":"Reactive Programming","link":"#reactive-programming","contents":[{"text":"Javelin","link":"https://github.com/hoplon/javelin"},{"text":"Reagi","link":"https://github.com/weavejester/reagi"},{"text":"rx-cljs","link":"https://github.com/leonardoborges/rx-cljs"},{"text":"Yolk","link":"https://github.com/Cicayda/yolk"}]},{"text":"Routing","link":"#routing","contents":[{"text":"Bidi","link":"https://github.com/juxt/bidi"},{"text":"Secretary","link":"https://github.com/gf3/secretary"},{"text":"Silk","link":"https://github.com/DomKM/silk"}]},{"text":"State Management","link":"#state-management","contents":[{"text":"hodgepodge","link":"http://funcool.github.io/hodgepodge/"},{"text":"plato","link":"https://github.com/eneroth/plato"},{"text":"storage-atom","link":"https://github.com/alandipert/storage-atom"},{"text":"Waltz","link":"https://github.com/ibdknox/waltz"}]},{"text":"Testing","link":"#testing","contents":[{"text":"cljs.test","link":"https://github.com/clojure/clojurescript/wiki/Testing"},{"text":"Expectations","link":"http://jayfields.com/expectations/"},{"text":"Speclj","link":"https://github.com/slagyr/speclj"},{"text":"test.check","link":"https://github.com/clojure/test.check"}]},{"text":"Validation","link":"#validation","contents":[{"text":"Bouncer","link":"https://github.com/leonardoborges/bouncer"},{"text":"Validateur","link":"http://clojurevalidations.info/"}]},{"text":"Web Framework & Template","link":"#web-framework--template","contents":[]},{"text":"Web Socket","link":"#web-socket","contents":[{"text":"Sente","link":"https://github.com/ptaoussanis/sente"}]}]