[{"text":"Apps","link":"#apps","contents":[]},{"text":"Boilerplates","link":"#boilerplates","contents":[{"text":"electron-boilerplate","link":"https://github.com/sindresorhus/electron-boilerplate"},{"text":"generator-electron","link":"https://github.com/sindresorhus/generator-electron"},{"text":"electron-boilerplate","link":"https://github.com/szwacz/electron-boilerplate"},{"text":"electron-react-boilerplate","link":"https://github.com/chentsulin/electron-react-boilerplate"},{"text":"descjop","link":"https://github.com/karad/lein_template_descjop"},{"text":"electron-quick-start","link":"https://github.com/electron/electron-quick-start"},{"text":"bozon","link":"https://github.com/railsware/bozon"},{"text":"electron-vue","link":"https://github.com/SimulatedGREG/electron-vue"},{"text":"SkelEktron","link":"https://github.com/BZCoding/SkelEktron"}]},{"text":"Tools","link":"#tools","contents":[]},{"text":"Components","link":"#components","contents":[{"text":"Photon","link":"http://photonkit.com"},{"text":"React PhotonKit","link":"https://github.com/react-photonkit/react-photonkit"},{"text":"menubar","link":"https://github.com/maxogden/menubar"},{"text":"cookies","link":"https://github.com/hstove/electron-cookies"},{"text":"window","link":"https://github.com/jprichardson/electron-window"},{"text":"React Desktop","link":"https://github.com/gabrielbull/react-desktop"},{"text":"electron-input-menu","link":"https://github.com/parro-it/electron-input-menu"},{"text":"chrome-tabs","link":"https://github.com/adamschwartz/chrome-tabs"},{"text":"titlebar","link":"https://github.com/kapetan/titlebar"}]},{"text":"Documentation","link":"#documentation","contents":[{"text":"Quick Start","link":"http://electron.atom.io/docs/tutorial/quick-start/"},{"text":"Official docs","link":"http://electron.atom.io/docs/"},{"text":"Essential Electron","link":"http://jlord.us/essential-electron/"}]},{"text":"Articles","link":"#articles","contents":[{"text":"Electron Fundamentals","link":"http://maxogden.com/electron-fundamentals.html"},{"text":"Building a desktop application with Electron","link":"https://medium.com/@bojzi/building-a-desktop-application-with-electron-204203eeb658"},{"text":"Codesigning your app for macOS","link":"http://jbavari.github.io/blog/2015/08/14/codesigning-electron-applications/"},{"text":"Auto-updating apps for macOS and Windows: The complete guide","link":"https://medium.com/@svilen/auto-updating-apps-for-windows-and-osx-using-electron-the-complete-guide-4aa7a50b904c"},{"text":"How To Make Your Electron App Sexy","link":"https://blog.dcpos.ch/how-to-make-your-electron-app-sexy"},{"text":"Electron Rocks!","link":"http://electron.rocks"}]},{"text":"Books","link":"#books","contents":[{"text":"Developing an Electron Edge","link":"https://bleedingedgepress.com/developing-an-electron-edge/"}]},{"text":"Videos","link":"#videos","contents":[{"text":"Creating Desktop Apps with Electron","link":"https://www.youtube.com/watch?v=ojX5yz35v4M"},{"text":"Packaging and Distributing Electron Desktop Apps","link":"https://www.youtube.com/watch?v=dz5SnmBzBXc"},{"text":"Multi Window Electron Desktop Apps","link":"https://www.youtube.com/watch?v=K-H2amwQ_pU"},{"text":"The State of Electron","link":"https://www.youtube.com/watch?v=RaPmi-33rfc"},{"text":"Cross-Platform Desktop Apps with Electron","link":"https://www.youtube.com/watch?v=9xX_G0l5jLU"},{"text":"Building Native Desktop apps using Electron","link":"https://www.youtube.com/watch?v=nXIrFq5-FC8"},{"text":"The New Desktop: Electron, React, & Pixel-Perfect Native-Feeling Experiences","link":"https://www.youtube.com/watch?v=jRPUB-D1Wx0"},{"text":"Getting Started with Electron 1.x","link":"https://www.youtube.com/watch?v=jKzBJAowmGg"},{"text":"Building Desktop Apps with Node.js and Electron","link":"https://www.youtube.com/watch?v=rbSvc8_BHaw"},{"text":"Electron Fundamentals course - Pluralsight","link":"https://www.pluralsight.com/courses/electron-fundamentals"}]},{"text":"Podcasts","link":"#podcasts","contents":[{"text":"JavaScript Jabber: Electron with Jessica Lord and Amy Palamountain","link":"https://devchat.tv/js-jabber/193-jsj-electron-with-jessica-lord-and-amy-palamountain"},{"text":"Hanselminutes: Creating cross-platform Electron apps with Jessica Lord","link":"http://hanselminutes.com/534/creating-cross-platform-electron-apps-with-jessica-lord"},{"text":"JavaScript Air: Electron Apps with @jlord and @emorikawa","link":"https://javascriptair.com/episodes/2016-07-06"},{"text":"The Changelog #216: GitHub's Electron with Zeke Sikelianos","link":"https://changelog.com/216/"},{"text":"Full Stack Radio #48: Jessica Lord - Building Desktop Apps with Electron","link":"http://www.fullstackradio.com/48"}]},{"text":"Community","link":"#community","contents":[{"text":"Discuss","link":"https://discuss.atom.io/c/electron"},{"text":"Reddit","link":"https://www.reddit.com/r/electronjs"},{"text":"Stack Overflow","link":"http://stackoverflow.com/questions/tagged/electron"},{"text":"@electronjs on Twitter","link":"https://twitter.com/electronjs"},{"text":"#atom-shell on Freenode","link":"http://webchat.freenode.net/?channels=atom-shell"},{"text":"#electron on Atom Slack","link":"http://atom-slack.herokuapp.com"},{"text":"electron-jp","link":"https://electron-jp-slackin.herokuapp.com"},{"text":"electron-br","link":"https://electron-br.slack.com"},{"text":"electron-kr","link":"http://www.meetup.com/electronkr"}]},{"text":"Tips","link":"#tips","contents":[]}]