[{"text":"General","link":"#general","contents":[{"text":"ASP.NET Core Documentation","link":"https://docs.asp.net/en/latest/"},{"text":".NET Core Documentation","link":"https://docs.microsoft.com/en-us/dotnet/articles/welcome"},{"text":".NET Core SDK","link":"https://www.microsoft.com/net/core"},{"text":".NET Platform Standard","link":"https://github.com/dotnet/corefx/blob/master/Documentation/architecture/net-platform-standard.md"}]},{"text":"Frameworks, Libraries and Tools  ","link":"#frameworks-libraries-and-tools","contents":[{"text":"API","link":"#api","contents":[{"text":"autorest","link":"https://github.com/Azure/autorest"},{"text":"LightNode","link":"https://github.com/neuecc/LightNode"},{"text":"NSwag","link":"https://github.com/NSwag/NSwag"},{"text":"RESTClient .NET","link":"https://bitbucket.org/MelbourneDeveloper/restclient-.net"},{"text":"Swashbuckle","link":"https://github.com/domaindrivendev/Ahoy"},{"text":"WebAPIContrib for ASP.NET CORE","link":"https://github.com/WebApiContrib/WebAPIContrib.Core"},{"text":"GraphQL","link":"https://github.com/mkmarek/graphql-dotnetcore","contents":[{"text":"graphql-dotnetcore","link":"https://github.com/mkmarek/graphql-dotnetcore"},{"text":"graphql-dotnet","link":"https://github.com/graphql-dotnet/graphql-dotnet"},{"text":"parser","link":"https://github.com/graphql-dotnet/parser"}]}]},{"text":"Application Frameworks","link":"#application-frameworks","contents":[{"text":"ASP.NET MVC","link":"https://github.com/aspnet/Mvc"},{"text":"ExtCore","link":"https://github.com/ExtCore"},{"text":"grpc","link":"https://github.com/grpc/grpc/tree/master/src/csharp"},{"text":"Nancy","link":"https://github.com/NancyFx/Nancy"}]},{"text":"Application Templates","link":"#application-templates","contents":[{"text":"ASP.NET MVC Boilerplate","link":"https://github.com/RehanSaeed/ASP.NET-MVC-Boilerplate"}]},{"text":"Authentication and Authorization","link":"#authentication-and-authorization","contents":[{"text":"Identity","link":"https://github.com/aspnet/Identity"},{"text":"IdentityServer - IdentityServer for ASP.NET Core 1.0","link":"https://github.com/IdentityServer/IdentityServer4","contents":[{"text":"20|20 IdentityServer4.EntityFrameworkCore","link":"https://github.com/2020IP/TwentyTwenty.IdentityServer4.EntityFrameworkCore"}]},{"text":"openiddict","link":"https://github.com/openiddict/openiddict-core"},{"text":"stormpath-sdk","link":"https://github.com/stormpath/stormpath-sdk-dotnet"}]},{"text":"Build Automation","link":"#build-automation","contents":[{"text":"cake-build","link":"https://github.com/cake-build/cake"},{"text":"Colorful.Console","link":"https://github.com/tomakita/Colorful.Console"},{"text":"go-dotnet","link":"https://github.com/matiasinsaurralde/go-dotnet"},{"text":"msbuild","link":"https://github.com/Microsoft/msbuild"},{"text":"vsts-agent","link":"https://github.com/Microsoft/vsts-agent/blob/master/README.md"}]},{"text":"Bundling and Minification","link":"#bundling-and-minification","contents":[{"text":"BundlerMinifier","link":"https://github.com/madskristensen/BundlerMinifier"},{"text":"JavaScriptViewEngine","link":"https://github.com/pauldotknopf/JavaScriptViewEngine"},{"text":"Smidge","link":"https://github.com/Shazwazza/Smidge/"},{"text":"Web Markup Minifier","link":"https://github.com/Taritsyn/WebMarkupMin"}]},{"text":"Caching","link":"#caching","contents":[{"text":"CacheManager","link":"https://github.com/MichaCo/CacheManager"},{"text":"Microsoft Caching","link":"https://github.com/aspnet/Caching"},{"text":"Stack Exchange Redis","link":"https://github.com/StackExchange/StackExchange.Redis"}]},{"text":"Cryptography","link":"#cryptography","contents":[{"text":"BCrypt.NET-Core","link":"https://github.com/neoKushan/BCrypt.Net-Core"},{"text":"BouncyCastle PCL","link":"https://github.com/onovotny/BouncyCastle-PCL"}]},{"text":"CMS","link":"#cms","contents":[{"text":"OrchardCMS2","link":"https://github.com/OrchardCMS/Orchard2"},{"text":"Platformus","link":"https://github.com/Platformus"},{"text":"SimpleContent","link":"https://github.com/joeaudette/cloudscribe.SimpleContent"}]},{"text":"Code Analysis and Metrics","link":"#code-analysis-and-metrics","contents":[{"text":"Audit.NET","link":"https://github.com/thepirat000/Audit.NET"},{"text":"NBench","link":"https://github.com/petabridge/NBench/tree/dev"},{"text":"OpenCover","link":"https://github.com/OpenCover/opencover"},{"text":"AspNet.Metrics","link":"https://github.com/alhardy/aspnet-metrics"}]},{"text":"Database Drivers","link":"#database-drivers","contents":[{"text":"LiteDB","link":"https://github.com/mbdavid/LiteDB"},{"text":"MongoDB.Driver","link":"https://github.com/mongodb/mongo-csharp-driver"},{"text":"Neo4jClient","link":"https://github.com/Readify/Neo4jClient/tree/DotNetCore"},{"text":"npgsql","link":"https://github.com/npgsql/npgsql"},{"text":"ravendb","link":"https://github.com/ayende/ravendb/tree/v4.0"},{"text":"RethinkDb.Driver","link":"https://github.com/bchavez/RethinkDb.Driver"}]},{"text":"E-Commerce and Payments","link":"#e-commerce-and-payments","contents":[{"text":"SimplCommerce","link":"https://github.com/simplcommerce/SimplCommerce"}]},{"text":"Graphics","link":"#graphics","contents":[{"text":"ImageProcessor","link":"https://github.com/JimBobSquarePants/ImageProcessor"}]},{"text":"Functional Reactive Programming","link":"#functional-reactive-programming","contents":[{"text":"ReactiveUI","link":"https://github.com/reactiveui/ReactiveUI"},{"text":"Rx.NET","link":"https://github.com/Reactive-Extensions/Rx.NET"},{"text":"sodium","link":"https://github.com/SodiumFRP/sodium/tree/master/c%23"}]},{"text":"IDE","link":"#ide","contents":[{"text":"rider","link":"https://www.jetbrains.com/rider/"},{"text":"Omnisharp","link":"http://www.omnisharp.net/"},{"text":"Visual Studio Code","link":"https://github.com/Microsoft/vscode"},{"text":"Visual Studio Community","link":"https://www.visualstudio.com/en-us/products/visual-studio-community-vs.aspx"}]},{"text":"Internationalization","link":"#internationalization","contents":[{"text":"Localization","link":"https://github.com/aspnet/Localization"},{"text":"nodatime","link":"https://github.com/nodatime/nodatime"}]},{"text":"IOC","link":"#ioc","contents":[{"text":"Autofac","link":"https://github.com/autofac/Autofac"},{"text":"DryIoc","link":"https://bitbucket.org/dadhi/dryioc"},{"text":"LightInject","link":"https://github.com/seesharper/LightInject"},{"text":"SimpleInjector","link":"https://github.com/simpleinjector/SimpleInjector"},{"text":"StructureMap","link":"https://github.com/structuremap/structuremap.dnx"}]},{"text":"Logging","link":"#logging","contents":[{"text":"common-logging","link":"https://github.com/net-commons/common-logging"},{"text":"dnxcore-logging-logstash","link":"https://github.com/jvandevelde/dnxcore-logging-logstash"},{"text":"serilog","link":"https://github.com/serilog/serilog"},{"text":"NLog","link":"https://github.com/NLog/NLog"},{"text":"Q42.Logging.ApplicationInsights","link":"https://github.com/Q42/Q42.Logging.ApplicationInsights"}]},{"text":"Mail","link":"#mail","contents":[{"text":"MailKit","link":"https://github.com/jstedfast/MailKit"},{"text":"PreMailer.Net","link":"https://github.com/milkshakesoftware/PreMailer.Net/tree/dotnet-core"},{"text":"MimeKit","link":"https://github.com/jstedfast/MimeKit"}]},{"text":"Mathematics","link":"#mathematics","contents":[{"text":"UnitConversion","link":"https://github.com/Stratajet/UnitConversion"}]},{"text":"Misc","link":"#misc","contents":[{"text":"AutoMapper","link":"https://github.com/AutoMapper/AutoMapper"},{"text":"Castle.Core","link":"https://github.com/castleproject/Core/tree/netcore"},{"text":"CommonMark.NET","link":"https://github.com/Knagis/CommonMark.NET"},{"text":"consuldotnet","link":"https://github.com/PlayFab/consuldotnet/tree/develop"},{"text":"CoreWF","link":"https://github.com/dmetzgar/corewf/"},{"text":"datatables","link":"https://github.com/ALMMa/datatables.aspnet/tree/dev"},{"text":"Docker.DotNet","link":"https://github.com/Microsoft/Docker.DotNet"},{"text":"FluentValidation","link":"https://github.com/JeremySkinner/FluentValidation"},{"text":"Humanizer","link":"https://github.com/Humanizr/Humanizer"},{"text":"language-ext","link":"https://github.com/louthy/language-ext"},{"text":"markdig","link":"https://github.com/lunet-io/markdig"},{"text":"Microphone","link":"https://github.com/rogeralsing/Microphone"},{"text":"NReco.LambdaParser","link":"https://github.com/nreco/lambdaparser"},{"text":"NReco.PivotData","link":"https://www.nuget.org/packages/NReco.PivotData/"},{"text":"reCAPTCHA","link":"https://github.com/PaulMiami/reCAPTCHA"},{"text":"PreStorm","link":"https://github.com/jshirota/PreStorm"},{"text":"Polly","link":"https://github.com/App-vNext/Polly"},{"text":"Scrutor","link":"https://github.com/khellang/Scrutor"}]},{"text":"ORM","link":"#orm","contents":[{"text":"Entity Framework Core","link":"https://github.com/aspnet/EntityFramework"},{"text":"Dapper - Simple object mapper for .NET.","link":"https://github.com/StackExchange/dapper-dot-net/tree/netstandard","contents":[{"text":"Dapper-FluentMap","link":"https://github.com/henkmollema/Dapper-FluentMap"},{"text":"Dommel","link":"https://github.com/henkmollema/Dommel"}]},{"text":"Limebean","link":"https://nick-lucas.github.io/LimeBean/"},{"text":"NEventStore","link":"https://github.com/NEventStore/NEventStore/tree/feature/dotnetcore"},{"text":"NoDb","link":"https://github.com/joeaudette/NoDb"},{"text":"NPoco","link":"https://github.com/schotime/NPoco"},{"text":"NReco.Data","link":"https://github.com/nreco/data"},{"text":"SqlFu","link":"https://github.com/sapiens/SqlFu"},{"text":"yessql","link":"https://github.com/sebastienros/yessql"}]},{"text":"Profiling","link":"#profiling","contents":[{"text":"Glimpse","link":"http://getglimpse.com"}]},{"text":"Queue and Messaging","link":"#queue-and-messaging","contents":[{"text":"MediatR - Simple, unambitious mediator implementation in .NET.","link":"https://github.com/jbogard/MediatR","contents":[{"text":"MediatR.Extensions.Microsoft.DependencyInjection","link":"https://github.com/jbogard/MediatR.Extensions.Microsoft.DependencyInjection"}]},{"text":"MicroBus","link":"https://github.com/Lavinski/Enexure.MicroBus"},{"text":"rabbitmq-dotnet-client","link":"https://github.com/rabbitmq/rabbitmq-dotnet-client"},{"text":"RawRabbit","link":"https://github.com/pardahlman/RawRabbit"},{"text":"Restbus","link":"http://restbus.org"},{"text":"netmq","link":"https://github.com/zeromq/netmq"}]},{"text":"Scheduler and Job","link":"#scheduler-and-job","contents":[{"text":"HangfireIO","link":"https://github.com/HangfireIO/Hangfire"},{"text":"quartznet","link":"https://github.com/quartznet/quartznet/tree/quartznet-3"},{"text":"Chroniton.NetCore","link":"https://github.com/leosperry/Chroniton"}]},{"text":"SDKs","link":"#sdks","contents":[{"text":"NetTelegramBotApi","link":"https://github.com/justdmitry/NetTelegramBotApi"},{"text":"octokit.net","link":"https://github.com/octokit/octokit.net/tree/target-the-coreclr"},{"text":"Open-XML-SDK-for-NET-Platform-Standard","link":"https://github.com/xrkolovos/Open-XML-SDK-for-NET-Platform-Standard"},{"text":"tweetinvi","link":"https://github.com/linvi/tweetinvi/tree/tweetinvi.netcore"}]},{"text":"Security","link":"#security","contents":[{"text":"HtmlSanitizer","link":"https://github.com/mganss/HtmlSanitizer"},{"text":"jose-jwt","link":"https://github.com/dvsekhvalnov/jose-jwt"},{"text":"NWebsec","link":"https://github.com/NWebsec/NWebsec"},{"text":"Security","link":"https://github.com/aspnet/Security"}]},{"text":"Searching","link":"#searching","contents":[{"text":"Elasticsearch.Net & NEST","link":"https://github.com/elastic/elasticsearch-net"},{"text":"ElasticsearchCRUD","link":"https://github.com/damienbod/ElasticsearchCRUD"},{"text":"AngleSharp","link":"https://github.com/AngleSharp/AngleSharp"},{"text":"SolrExpress","link":"https://github.com/solr-express/solr-express"}]},{"text":"Serialization","link":"#serialization","contents":[{"text":"Channels","link":"https://github.com/davidfowl/Channels"},{"text":"CsvHelper","link":"https://github.com/JoshClose/CsvHelper"},{"text":"msgpack-cli","link":"https://github.com/msgpack/msgpack-cli"},{"text":"Newtonsoft.Json","link":"https://github.com/JamesNK/Newtonsoft.Json"},{"text":"protobuf-net","link":"https://github.com/mgravell/protobuf-net/"},{"text":"TinyCsvParser","link":"https://github.com/bytefish/TinyCsvParser"},{"text":"YamlDotNet","link":"https://github.com/aaubry/YamlDotNet"}]},{"text":"Testing","link":"#testing","contents":[{"text":"Bogus","link":"https://github.com/bchavez/Bogus"},{"text":"GenFu","link":"https://github.com/MisterJames/GenFu"},{"text":"FakeItEasy","link":"https://github.com/FakeItEasy/FakeItEasy"},{"text":"FluentAssertions","link":"https://github.com/dennisdoomen/FluentAssertions"},{"text":"moq.netcore","link":"https://github.com/aspnet/moq4/tree/netcore"},{"text":"MSpec","link":"https://github.com/machine/machine.specifications"},{"text":"MyTested.AspNetCore.Mvc","link":"https://github.com/ivaylokenov/MyTested.AspNetCore.Mvc"},{"text":"Netling","link":"https://github.com/hallatore/Netling"},{"text":"nunit","link":"https://github.com/nunit/dotnet-test-nunit"},{"text":"shouldly","link":"https://github.com/shouldly/shouldly"},{"text":"SpecFlow","link":"https://github.com/techtalk/SpecFlow/tree/DotNetCore"},{"text":"TestStack.BDDfy","link":"https://github.com/TestStack/TestStack.BDDfy"},{"text":"xunit","link":"https://github.com/xunit/xunit"}]},{"text":"Tools","link":"#tools","contents":[{"text":"gitignore.io","link":"https://github.com/joeblau/gitignore.io"}]},{"text":"Web Framework","link":"#web-framework","contents":[{"text":"ReactJS.NET","link":"https://github.com/reactjs/React.NET"}]},{"text":"Web Socket","link":"#web-socket","contents":[{"text":"SignalR Server","link":"https://github.com/aspnet/SignalR-Server"},{"text":"WampSharp","link":"https://github.com/Code-Sharp/WampSharp"}]},{"text":"Windows Service","link":"#windows-service","contents":[{"text":"Topshelf","link":"https://github.com/Topshelf/Topshelf"}]}]},{"text":"Starter Kits","link":"#starter-kits","contents":[{"text":"ASP.NET Core Starter Kit","link":"https://github.com/kriasoft/aspnet-starter-kit"},{"text":"ASP.NET Boilerplate","link":"https://github.com/aspnetboilerplate/aspnetboilerplate"},{"text":"react-aspnet-boilerplate","link":"https://github.com/pauldotknopf/react-aspnet-boilerplate"},{"text":"saaskit","link":"https://github.com/saaskit/saaskit"}]},{"text":"Sample Projects","link":"#sample-projects","contents":[{"text":"AlbumViewerVNext","link":"https://github.com/RickStrahl/AlbumViewerVNext"},{"text":"allReady","link":"https://github.com/HTBox/allReady"},{"text":"AspNet5GeoElasticsearch","link":"https://github.com/damienbod/AspNet5GeoElasticsearch"},{"text":"aspnet-servicediscovery-patterns","link":"https://github.com/cecilphillip/aspnet-servicediscovery-patterns"},{"text":"cloudscribe","link":"https://github.com/joeaudette/cloudscribe"},{"text":"distributed-playground","link":"https://github.com/jvandevelde/distributed-playground"},{"text":"DotNetClub","link":"https://github.com/scheshan/DotNetClub"},{"text":"Entropy","link":"https://github.com/aspnet/Entropy"},{"text":"magazine-website","link":"https://github.com/thangchung/magazine-website"},{"text":"MegaMine","link":"https://github.com/Nootus/MegaMine"},{"text":"minicompiler","link":"Minification, bundling and compiling sample"},{"text":"MusicStore","link":"https://github.com/aspnet/MusicStore"},{"text":"ReactiveTraderCloud","link":"https://github.com/AdaptiveConsulting/ReactiveTraderCloud"},{"text":"PhotoGallery","link":"https://github.com/chsakell/aspnet5-angular2-typescript"},{"text":"Practical ASP.NET Core","link":"https://github.com/dodyg/practical-aspnetcore"}]},{"text":"Articles","link":"#articles","contents":[{"text":".NET Continuous Delivery Microservices","link":"http://stackshare.io/tomstaijen/net-continuous-delivery-microservices"},{"text":"Adding Travis CI builds to a .NET Core app","link":"http://andrewlock.net/adding-travis-ci-to-a-net-core-app/"},{"text":"ASP.NET Core 1.0 - Configure ApplicationInsights","link":"http://social.technet.microsoft.com/wiki/contents/articles/35918.asp-net-core-1-0-configure-applicationinsights.aspx"},{"text":"Authentication in ASP.NET Core","link":"https://stormpath.com/blog/authentication-asp-net-core"},{"text":"A guide to the .NET Core projects on GitHub","link":"https://blog.rendle.io/a-guide-to-the-net-projects-on-github/"},{"text":"A walk-through for an ASP.NET Authorization Lab","link":"https://github.com/blowdart/AspNetAuthorizationWorkshop"},{"text":"A very good example about EF Core","link":"https://github.com/rowanmiller/Demo-EFCore"},{"text":"haproxy, nginx, Angular 2, ASP.NET Core, Redis and Docker","link":"http://tattoocoder.azurewebsites.net/legion-of-heroes-haproxy-nginx-angular2-aspnetcore-redis-docker/"},{"text":"Porting .NET Framework Library to .NET Core","link":"http://www.michael-whelan.net/porting-dotnet-framework-library-to-dotnet-core"},{"text":"Publishing a .NET project with Appveyor and NuGet","link":"https://few-lines-of-code.blogspot.com/2016/03/publishing-net-project-with-appveyor.html"},{"text":"The New Configuration Model in ASP.NET Core","link":"http://developer.telerik.com/featured/new-configuration-model-asp-net-core/"},{"text":"Understanding ASP.NET Core Initialization","link":"http://developer.telerik.com/featured/understanding-asp-net-core-initialization/"},{"text":"here","link":"https://manuel-rauber.com/2016/03/07/node-js-asp-net-core-1-0-a-usage-comparison/"}]},{"text":"Books","link":"#books","contents":[{"text":"ASP.NET Core Application Development: Building an application in four sprints (Developer Reference)","link":"https://www.amazon.com/ASP-NET-Core-Application-Development-application/dp/1509304061"},{"text":"ASP.NET Core 1.0 High Performance","link":"https://www.amazon.com/ASP-NET-Core-1-0-High-Performance/dp/1785881892"},{"text":"Building Microservices with ASP.NET Core: Develop, Test, and Deploy Cross-Platform Services in the Cloud","link":"https://www.amazon.com/Building-Microservices-ASP-NET-Core-Cross-Platform/dp/1491961732"},{"text":"C# 6 and .NET Core 1.0: Modern Cross-Platform Development","link":"https://www.amazon.com/NET-Core-1-0-Cross-Platform-Development/dp/1785285696"},{"text":"Microservices in .NET Core: with C#, the Nancy framework, and OWIN middleware","link":"https://www.amazon.com/Microservices-NET-Core-framework-middleware/dp/1617293377"},{"text":"Professional C# 6 and .NET Core 1.0","link":"https://www.amazon.com/Professional-NET-Core-Christian-Nagel/dp/111909660X"},{"text":".NET Core in Action","link":"https://manning.com/books/dotnet-core-in-action"}]},{"text":"Videos","link":"#videos","contents":[{"text":"Channel9","link":"https://channel9.msdn.com"},{"text":"Visual Studio","link":"https://www.youtube.com/user/VisualStudio/channels"},{"text":".NET World","link":"https://www.youtube.com/channel/UClW5uIyHKPhfSEloQxn7b0Q"}]},{"text":"Podcasts","link":"#podcasts","contents":[{"text":".NET Rocks","link":"https://www.dotnetrocks.com"},{"text":"Static Void Podcast","link":"https://www.staticvoidpodcast.com"},{"text":"The sound of .NET","link":"http://thesoundof.net/?q=.NET+Core"}]},{"text":"Community","link":"#community","contents":[{"text":"ASP.NET","link":"https://forums.asp.net"},{"text":".NET Foundation","link":"http://forums.dotnetfoundation.org"},{"text":"Channel9","link":"https://channel9.msdn.com/Forums"},{"text":"Stack Overflow","link":"https://stackoverflow.com/questions/tagged/.net-core","contents":[{"text":".NET Core","link":"https://stackoverflow.com/questions/tagged/.net-core"},{"text":"CoreCLR","link":"https://stackoverflow.com/questions/tagged/coreclr"},{"text":"ASP.NET Core","link":"https://stackoverflow.com/questions/tagged/asp.net-core"},{"text":"ASP.NET Core MVC","link":"https://stackoverflow.com/questions/tagged/asp.net-core-mvc"},{"text":"ASP.NET Core 1.0","link":"https://stackoverflow.com/questions/tagged/asp.net-core-1.0"},{"text":"Entity Framework Core","link":"https://stackoverflow.com/questions/tagged/entity-framework-core"}]}]}]