[{"text":"Administration","link":"#administration","contents":[{"text":"AdminCrudBundle","link":"https://github.com/MWSimple/AdminCrudBundle"},{"text":"AdmingeneratorGeneratorBundle","link":"https://github.com/symfony2admingenerator/AdmingeneratorGeneratorBundle"},{"text":"EasyAdminBundle","link":"https://github.com/javiereguiluz/EasyAdminBundle"},{"text":"SonataAdminBundle","link":"https://github.com/sonata-project/SonataAdminBundle"}]},{"text":"Assets Management","link":"#assets-management","contents":[{"text":"assetic-extra-bundle","link":"https://github.com/alexandresalome/assetic-extra-bundle"},{"text":"AsseticInjectorBundle","link":"https://github.com/AppVentus/AsseticInjectorBundle"},{"text":"AsseticMinifierBundle","link":"https://github.com/Djeg/AsseticMinifierBundle"},{"text":"FkrCssURLRewriteBundle","link":"https://github.com/fkrauthan/FkrCssURLRewriteBundle"},{"text":"IgorwFileServeBundle","link":"https://github.com/igorw/IgorwFileServeBundle"},{"text":"JmikolaJsAssetsHelperBundle","link":"https://github.com/jmikola/JmikolaJsAssetsHelperBundle"},{"text":"KachkaevAssetsVersionBundle","link":"https://github.com/kachkaev/KachkaevAssetsVersionBundle"},{"text":"SalvaJshrinkBundle","link":"https://github.com/nibsirahsieu/SalvaJshrinkBundle"},{"text":"SpritesBundle","link":"https://github.com/pminnieur/SpritesBundle"},{"text":"ZakharovviHumansTxtBundle","link":"https://github.com/zakharovvi/ZakharovviHumansTxtBundle"}]},{"text":"Community","link":"#community","contents":[{"text":"1","link":"https://fb.com/groups/7672226565","contents":[{"text":"1","link":"https://fb.com/groups/7672226565"},{"text":"2","link":"https://fb.com/groups/symfony2.framework"}]},{"text":"Google+","link":"https://plus.google.com/communities/109013871316146116610"},{"text":"#symfony","link":"http://irc.lc/freenode/symfony","contents":[{"text":"#symfony","link":"http://irc.lc/freenode/symfony"},{"text":"#symfony-docs","link":"http://irc.lc/freenode/symfony"}]},{"text":"Linked.in","link":"https://www.linkedin.com/grp/home?gid=29205"},{"text":"Community events","link":"http://symfony.com/events/","contents":[{"text":"Community events","link":"http://symfony.com/events/"},{"text":"Meetup","link":"http://www.meetup.com/topics/symfony/"}]},{"text":"Quora","link":"https://www.quora.com/topic/Symfony"},{"text":"Reddit","link":"https://www.reddit.com/r/symfony"},{"text":"SensioLabs Connect","link":"https://connect.sensiolabs.com/login"},{"text":"Slack","link":"https://symfony2slack.herokuapp.com/"},{"text":"Stack Overflow","link":"http://stackoverflow.com/questions/tagged/symfony2"},{"text":"Twitter","link":"https://twitter.com/symfony"}]},{"text":"Development","link":"#development","contents":[{"text":"AccessibleBundle","link":"https://github.com/antares993/AccessibleBundle"},{"text":"ApiExceptionBundle","link":"https://github.com/M6Web/ApiExceptionBundle"},{"text":"AvAjaxBundle","link":"https://github.com/AppVentus/AvAjaxBundle"},{"text":"BeelabTestBundle","link":"https://github.com/Bee-Lab/BeelabTestBundle"},{"text":"CacheAdministrationBundle","link":"https://github.com/yamiko-ninja/CacheAdministrationBundle"},{"text":"ControllerExtraBundle","link":"https://github.com/mmoreram/ControllerExtraBundle"},{"text":"DunglasActionBundle","link":"https://github.com/dunglas/DunglasActionBundle"},{"text":"http-bundle","link":"https://github.com/iltar/http-bundle"},{"text":"JMSDebuggingBundle","link":"http://jmsyst.com/bundles/JMSDebuggingBundle"},{"text":"LadybugBundle","link":"https://github.com/raulfraile/LadybugBundle"},{"text":"LiipCodeBundle","link":"https://github.com/liip/LiipCodeBundle"},{"text":"LiipFunctionalTestBundle","link":"https://github.com/liip/LiipFunctionalTestBundle"},{"text":"ListenersDebugCommandBundle","link":"https://github.com/egulias/ListenersDebugCommandBundle"},{"text":"ParamConverterBundle","link":"https://github.com/jakzal/ParamConverterBundle"},{"text":"PhpMetricsCollectorBundle","link":"https://github.com/phpmetrics/PhpMetricsCollectorBundle"},{"text":"PsyshBundle","link":"https://github.com/theofidry/PsyshBundle"},{"text":"PUGXGeneratorBundle","link":"https://github.com/PUGX/PUGXGeneratorBundle"},{"text":"redaktilo-bundle","link":"https://github.com/gnugat/redaktilo-bundle"},{"text":"SandboxBundle","link":"https://github.com/danrevah/sandbox-bundle"},{"text":"StatsDClientBundle","link":"https://github.com/liuggio/StatsDClientBundle"},{"text":"TagDebugCommandBundle","link":"https://github.com/egulias/TagDebugCommandBundle"},{"text":"TwigReflectionBundle","link":"https://github.com/arnaud-lb/TwigReflectionBundle"},{"text":"WebfactoryExceptionsBundle","link":"https://github.com/webfactory/exceptions-bundle"},{"text":"WebProfilerExtraBundle","link":"https://github.com/Elao/WebProfilerExtraBundle"},{"text":"XhprofBundle","link":"https://github.com/jonaswouters/XhprofBundle"}]},{"text":"Distributions","link":"#distributions","contents":[{"text":"API Platform framework","link":"https://github.com/api-platform/api-platform"},{"text":"KnpLabs RAD Edition","link":"https://github.com/KnpLabs/rad-edition"},{"text":"Kunstmaan Bundles Standard Edition","link":"https://github.com/Kunstmaan/KunstmaanBundlesStandardEdition"},{"text":"Liip RAD Edition","link":"https://github.com/liip/symfony-rad-edition"},{"text":"Symfony Biga Edition","link":"https://github.com/JoshuaEstes/symfony-biga-edition"},{"text":"Symfony Bootstrap Edition","link":"https://github.com/phiamo/symfony-bootstrap"},{"text":"Symfony CMF Standard Edition","link":"https://github.com/symfony-cmf/standard-edition"},{"text":"Symfony EmberJs Edition","link":"https://github.com/ucsf-ckm/symfony-emberjs-edition"},{"text":"Symfony Empty Edition","link":"https://github.com/gnugat/symfony-empty-edition"},{"text":"Symfony Micro Edition","link":"https://github.com/magnusnordlander/symfony-micro"},{"text":"Symfony REST Edition","link":"https://github.com/gimler/symfony-rest-edition"},{"text":"Symfony Sonata Edition","link":"https://github.com/jmather/symfony-sonata-distribution"},{"text":"Symfony Standard Edition","link":"https://github.com/symfony/symfony-standard"},{"text":"Victoire DCMS","link":"https://github.com/victoire/victoire"}]},{"text":"Ecommerce","link":"#ecommerce","contents":[{"text":"Bamboo","link":"https://github.com/elcodi/bamboo"},{"text":"Elcodi","link":"https://github.com/elcodi/elcodi"},{"text":"WellCommerce","link":"https://github.com/WellCommerce/WellCommerce"},{"text":"Sylius","link":"https://github.com/Sylius/Sylius"}]},{"text":"Forms","link":"#forms","contents":[{"text":"AutoFormFillBundle","link":"https://github.com/AppVentus/AutoFormFillBundle"},{"text":"CaptchaBundle","link":"https://github.com/Gregwar/CaptchaBundle"},{"text":"ContactBundle","link":"https://github.com/mremi/ContactBundle"},{"text":"CraueFormFlowBundle","link":"https://github.com/craue/CraueFormFlowBundle"},{"text":"FilterFormBundle","link":"https://github.com/IDCI-Consulting/FilterFormBundle"},{"text":"FormBundle","link":"https://github.com/Gregwar/FormBundle"},{"text":"InfiniteFormBundle","link":"https://github.com/infinite-networks/InfiniteFormBundle"},{"text":"IvoryCKEditorBundle","link":"https://github.com/egeloen/IvoryCKEditorBundle"},{"text":"IvoryOrderedFormBundle","link":"https://github.com/egeloen/IvoryOrderedFormBundle"},{"text":"LexikFormFilterBundle","link":"https://github.com/lexik/LexikFormFilterBundle"},{"text":"SharkLoggerBundle","link":"https://github.com/agiuliano/SharkLoggerBundle"}]},{"text":"Internationalization","link":"#internationalization","contents":[{"text":"BazingaJsTranslationBundle","link":"https://github.com/willdurand/BazingaJsTranslationBundle"},{"text":"JMSI18nRoutingBundle","link":"http://jmsyst.com/bundles/JMSI18nRoutingBundle"},{"text":"JMSTranslationBundle","link":"http://jmsyst.com/bundles/JMSTranslationBundle"},{"text":"LexikTranslationBundle","link":"https://github.com/lexik/LexikTranslationBundle"},{"text":"LuneticsLocaleBundle","link":"https://github.com/lunetics/LocaleBundle"},{"text":"TimezoneBundle","link":"https://github.com/lunetics/TimezoneBundle"},{"text":"TranslationFormBundle","link":"https://github.com/a2lix/TranslationFormBundle"}]},{"text":"Miscellaneous","link":"#miscellaneous","contents":[{"text":"AnhTaggableBundle","link":"https://github.com/hilobok/AnhTaggableBundle"},{"text":"AntennaBundle","link":"https://github.com/flint/AntennaBundle"},{"text":"APYBreadcrumbTrailBundle","link":"https://github.com/Abhoryo/APYBreadcrumbTrailBundle"},{"text":"APYDataGridBundle","link":"https://github.com/APY/APYDataGridBundle"},{"text":"AvAlertifyBundle","link":"https://github.com/AppVentus/AvAlertifyBundle"},{"text":"AviaryBundle","link":"https://github.com/AppVentus/AviaryBundle"},{"text":"AvListBundle","link":"https://github.com/AppVentus/AvListBundle"},{"text":"BackupManagerBundle","link":"https://github.com/lhpalacio/BackupManagerBundle"},{"text":"BazingaFakerBundle","link":"https://github.com/willdurand/BazingaFakerBundle"},{"text":"BazingaGeocoderBundle","link":"https://github.com/geocoder-php/BazingaGeocoderBundle"},{"text":"BCCMyrrixBundle","link":"https://github.com/michelsalib/BCCMyrrixBundle"},{"text":"BGBarcodeBundle","link":"https://github.com/paterik/BGBarcodeBundle"},{"text":"BlogBundle","link":"https://github.com/stfalcon/BlogBundle"},{"text":"bootstrap-bundle","link":"https://github.com/braincrafted/bootstrap-bundle"},{"text":"BreadcrumbsBundle","link":"https://github.com/whiteoctober/BreadcrumbsBundle"},{"text":"BrowscapBundle","link":"https://github.com/browscap/BrowscapBundle"},{"text":"CacheToolBundle","link":"https://github.com/gordalina/CacheToolBundle"},{"text":"CarbonBundle","link":"https://github.com/lightsuner/CarbonBundle"},{"text":"CheckBundles","link":"https://github.com/wjzijderveld/CheckBundles"},{"text":"CloudBackupBundle","link":"https://github.com/dizda/CloudBackupBundle"},{"text":"ConsoleBundle","link":"https://github.com/CoreSphere/ConsoleBundle"},{"text":"CsaGuzzleBundle","link":"https://github.com/csarrazi/CsaGuzzleBundle"},{"text":"CsvBundle","link":"https://github.com/EGYG33K/CsvBundle"},{"text":"DomainParserBundle","link":"https://github.com/EGYG33K/DomainParserBundle"},{"text":"EasyAuditBundle","link":"http://xiidea.github.io/EasyAuditBundle/"},{"text":"EmbedlyBundle","link":"https://github.com/EmanueleMinotto/EmbedlyBundle"},{"text":"ExcelBundle","link":"https://github.com/liuggio/ExcelBundle"},{"text":"FeatureToggleBundle","link":"https://github.com/marekkalnik/FeatureToggleBundle"},{"text":"ffmpeg-bundle","link":"https://github.com/pulse00/ffmpeg-bundle"},{"text":"FlorianvSwapBundle","link":"https://github.com/florianv/FlorianvSwapBundle"},{"text":"FMBbCodeBundle","link":"https://github.com/helios-ag/FMBbCodeBundle"},{"text":"FMElfinderBundle","link":"https://github.com/helios-ag/FMElfinderBundle"},{"text":"GnugatWizardBundle","link":"https://github.com/gnugat/GnugatWizardBundle"},{"text":"godfather","link":"https://github.com/PUGX/godfather"},{"text":"GoogleBundle","link":"https://github.com/antimattr/GoogleBundle"},{"text":"guzzle-bundle","link":"https://github.com/misd-service-development/guzzle-bundle"},{"text":"highcharts-bundle","link":"https://github.com/misd-service-development/highcharts-bundle"},{"text":"HTMLPurifierBundle","link":"https://github.com/arnaud-lb/HTMLPurifierBundle"},{"text":"IbrowsWizardAnnotationBundle","link":"https://github.com/ibrows/IbrowsWizardAnnotationBundle"},{"text":"ImageCropBundle","link":"https://github.com/anacona16/ImageCropBundle"},{"text":"JMDUnoconvBundle","link":"https://github.com/mops1k/JMDUnoconvBundle"},{"text":"KayueEssenceBundle","link":"https://github.com/kayue/KayueEssenceBundle"},{"text":"KitpagesDataGridBundle","link":"https://github.com/kitpages/KitpagesDataGridBundle"},{"text":"KnpMarkdownBundle","link":"https://github.com/KnpLabs/KnpMarkdownBundle"},{"text":"KnpSnappyBundle","link":"https://github.com/KnpLabs/KnpSnappyBundle"},{"text":"LexikMaintenanceBundle","link":"https://github.com/lexik/LexikMaintenanceBundle"},{"text":"LiipImagineBundle","link":"https://github.com/liip/LiipImagineBundle"},{"text":"LiipUrlAutoConverterBundle","link":"https://github.com/liip/LiipUrlAutoConverterBundle"},{"text":"marshaller-bundle","link":"https://github.com/gnugat/marshaller-bundle"},{"text":"metrics","link":"https://github.com/beberlei/metrics"},{"text":"MhorMediaInfoBundle","link":"https://github.com/mhor/MhorMediaInfoBundle"},{"text":"Mobile-Detect","link":"https://github.com/serbanghita/Mobile-Detect"},{"text":"MobileDetectBundle","link":"https://github.com/suncat2000/MobileDetectBundle"},{"text":"MultiParamBundle","link":"https://github.com/jaytaph/MultiParamBundle"},{"text":"ObHighchartsBundle","link":"https://github.com/marcaube/ObHighchartsBundle"},{"text":"OneupUploaderBundle","link":"https://github.com/1up-lab/OneupUploaderBundle"},{"text":"phone-number-bundle","link":"https://github.com/misd-service-development/phone-number-bundle"},{"text":"prezent-grid-bundle","link":"https://github.com/Prezent/prezent-grid-bundle"},{"text":"query-bus-bundle","link":"https://github.com/gnugat/query-bus-bundle"},{"text":"rss-atom-bundle","link":"https://github.com/alexdebril/rss-atom-bundle"},{"text":"Search-SphinxsearchBundle","link":"https://github.com/timewasted/Search-SphinxsearchBundle"},{"text":"SettingsBundle","link":"https://github.com/dmishh/SettingsBundle"},{"text":"shorturl-bundle","link":"https://github.com/fabstei/shorturl-bundle"},{"text":"SimpleArrayBundle","link":"https://github.com/EmanueleMinotto/SimpleArrayBundle"},{"text":"sphinx-realtime-bundle","link":"https://github.com/camdram/sphinx-realtime-bundle"},{"text":"SphinxsearchBundle","link":"https://github.com/IAkumaI/SphinxsearchBundle"},{"text":"StringGeneratorBundle","link":"https://github.com/vivait/StringGeneratorBundle"},{"text":"TbbcCacheBundle","link":"https://github.com/TheBigBrainsCompany/TbbcCacheBundle"},{"text":"TbbcMoneyBundle","link":"https://github.com/TheBigBrainsCompany/TbbcMoneyBundle"},{"text":"TemplatedUriBundle","link":"https://github.com/hautelook/TemplatedUriBundle"},{"text":"ThruwayBundle","link":"https://github.com/voryx/ThruwayBundle"},{"text":"timeline-bundle","link":"https://github.com/stephpy/timeline-bundle"},{"text":"TransmissionBundle","link":"https://github.com/labzone/TransmissionBundle"},{"text":"versioning-bundle","link":"https://github.com/shivas/versioning-bundle"},{"text":"VisithorBundle","link":"https://github.com/Visithor/VisithorBundle"},{"text":"WhiteOctoberPagerfantaBundle","link":"https://github.com/whiteoctober/WhiteOctoberPagerfantaBundle"},{"text":"WidopFrameworkExtraBundle","link":"https://github.com/widop/WidopFrameworkExtraBundle"},{"text":"WozbeRedirectBundle","link":"https://github.com/wozbe/WozbeRedirectBundle"}]},{"text":"Monitoring","link":"#monitoring","contents":[{"text":"LiipMonitorBundle","link":"https://github.com/liip/LiipMonitorBundle"},{"text":"SoclozMonitoringBundle","link":"https://github.com/SoCloz/SoclozMonitoringBundle"}]},{"text":"Payments Management","link":"#payments-management","contents":[{"text":"CartBundle","link":"https://github.com/leaphly/CartBundle"},{"text":"JMSPaymentCoreBundle","link":"http://jmsyst.com/bundles/JMSPaymentCoreBundle"},{"text":"JMSPaymentPaypalBundle","link":"https://github.com/schmittjoh/JMSPaymentPaypalBundle"},{"text":"MangopayBundle","link":"https://github.com/AppVentus/MangopayBundle"},{"text":"PaymentAdyenBundle","link":"https://github.com/ruudk/PaymentAdyenBundle"},{"text":"PayumBundle","link":"https://github.com/Payum/PayumBundle"}]},{"text":"Queues","link":"#queues","contents":[{"text":"BernardBundle","link":"https://github.com/bernardphp/BernardBundle"},{"text":"GearmanBundle","link":"http://gearmanbundle.readthedocs.org/en/latest/"},{"text":"HeriJobQueueBundle","link":"https://github.com/heristop/HeriJobQueueBundle"},{"text":"JMSJobQueueBundle","link":"http://jmsyst.com/bundles/JMSJobQueueBundle"},{"text":"LeezyPheanstalkBundle","link":"https://github.com/armetiz/LeezyPheanstalkBundle"},{"text":"qpush-bundle","link":"http://qpush-bundle.readthedocs.org/en/latest/"},{"text":"RabbitMqBundle","link":"https://github.com/videlalvaro/RabbitMqBundle"},{"text":"RSQueueBundle","link":"https://github.com/mmoreram/RSQueueBundle"}]},{"text":"Reading","link":"#reading","contents":[{"text":"Assets Cache Busting in Symfony","link":"http://elnur.pro/assets-cache-busting-in-symfony/"},{"text":"High Performance Websites with Symfony2","link":"http://slides.seld.be/?file=2011-10-20+High+Performance+Websites+with+Symfony2.html"},{"text":"Symfony - project tamed","link":"http://clearcode.cc/2014/03/symfony-project/"},{"text":"Symfony2 cheat sheet","link":"http://www.symfony2cheatsheet.com/"}]},{"text":"Resources","link":"#resources","contents":[{"text":"Symfony2 Service Config Converter","link":"http://converter.rosstuck.com/"},{"text":"Twigfiddle","link":"http://twigfiddle.com/"}]},{"text":"Service Container","link":"#service-container","contents":[{"text":"CraueConfigBundle","link":"https://github.com/craue/CraueConfigBundle"},{"text":"JMDSettingsBundle","link":"https://github.com/mops1k/settings-bundle"},{"text":"JMSDiExtraBundle","link":"http://jmsyst.com/bundles/JMSDiExtraBundle"},{"text":"KutnyAutowiringBundle","link":"https://github.com/kutny/autowiring-bundle"},{"text":"PHP-DI","link":"http://php-di.org"}]},{"text":"Storage","link":"#storage","contents":[{"text":"AliceBundle","link":"https://github.com/hautelook/AliceBundle"},{"text":"AliceFixturesBundle","link":"https://github.com/h4cc/AliceFixturesBundle"},{"text":"AvSpoolMailerBundle","link":"https://github.com/AppVentus/AvSpoolMailerBundle"},{"text":"doctrine-routing-bundle","link":"https://github.com/eschmar/doctrine-routing-bundle"},{"text":"DoctrineEncryptBundle","link":"https://github.com/vmelnik-ukraine/DoctrineEncryptBundle"},{"text":"DoctrineEnumBundle","link":"https://github.com/fre5h/DoctrineEnumBundle"},{"text":"DoctrineFixturesBundle","link":"https://github.com/doctrine/DoctrineFixturesBundle"},{"text":"DoctrineMigrationsBundle","link":"https://github.com/doctrine/DoctrineMigrationsBundle"},{"text":"elastica-query-bundle","link":"https://github.com/mapado/elastica-query-bundle"},{"text":"FeedBundle","link":"https://github.com/eko/FeedBundle"},{"text":"FPNTagBundle","link":"https://github.com/FabienPennequin/FPNTagBundle"},{"text":"GaufretteBrowserBundle","link":"https://github.com/digitalkaoz/GaufretteBrowserBundle"},{"text":"KnpGaufretteBundle","link":"https://github.com/KnpLabs/KnpGaufretteBundle"},{"text":"MysqlDoctrineFunctions","link":"https://github.com/mapado/MysqlDoctrineFunctions"},{"text":"OneupFlysystemBundle","link":"https://github.com/1up-lab/OneupFlysystemBundle"},{"text":"RelationBundle","link":"https://github.com/Ph3nol/RelationBundle"},{"text":"SncRedisBundle","link":"https://github.com/snc/SncRedisBundle"},{"text":"StofDoctrineExtensionsBundle","link":"https://github.com/stof/StofDoctrineExtensionsBundle"},{"text":"VichGeographicalBundle","link":"https://github.com/dustin10/VichGeographicalBundle"},{"text":"WizadDoctrineDocBundle","link":"https://github.com/wpottier/WizadDoctrineDocBundle"}]},{"text":"Template Engine","link":"#template-engine","contents":[{"text":"CgKintBundle","link":"https://github.com/carlos-granados/CgKintBundle"},{"text":"FlashAlertBundle","link":"https://github.com/rasanga/FlashAlertBundle"},{"text":"GravatarBundle","link":"https://github.com/henrikbjorn/GravatarBundle"},{"text":"KnpTimeBundle","link":"https://github.com/KnpLabs/KnpTimeBundle"},{"text":"swift-css-inliner-bundle","link":"https://github.com/toretto460/swift-css-inliner-bundle"},{"text":"TwigCacheBundle","link":"https://github.com/EmanueleMinotto/TwigCacheBundle"},{"text":"TwigExtraBundle","link":"https://github.com/csanquer/TwigExtraBundle"},{"text":"TwigInflectionBundle","link":"https://github.com/EmanueleMinotto/TwigInflectionBundle"},{"text":"TwigJackBundle","link":"https://github.com/boekkooi/TwigJackBundle"},{"text":"TwitalBundle","link":"https://github.com/goetas/twital-bundle"},{"text":"UcoTwigExtensionsBundle","link":"https://github.com/sgomez/UcoTwigExtensionsBundle"}]},{"text":"Third Party APIs","link":"#third-party-apis","contents":[{"text":"AlgoliaSearchBundle","link":"https://github.com/algolia/AlgoliaSearchBundle"},{"text":"CoopTilleulsOvhBundle","link":"https://github.com/coopTilleuls/CoopTilleulsOvhBundle"},{"text":"GordalinaMixpanelBundle","link":"https://github.com/gordalina/GordalinaMixpanelBundle"},{"text":"SwarrotBundle","link":"https://github.com/swarrot/SwarrotBundle"},{"text":"SwmMailHookBundle","link":"https://github.com/ScullWM/MailHookBundle/"},{"text":"YuccaPrerenderBundle","link":"https://github.com/rjanot/YuccaPrerenderBundle"}]},{"text":"User Management","link":"#user-management","contents":[{"text":"FOSUserBundle","link":"https://github.com/FriendsOfSymfony/FOSUserBundle"},{"text":"HWIOAuthBundle","link":"https://github.com/hwi/HWIOAuthBundle"},{"text":"JmikolaAutoLoginBundle","link":"https://github.com/jmikola/JmikolaAutoLoginBundle"},{"text":"JMSSecurityExtraBundle","link":"http://jmsyst.com/bundles/JMSSecurityExtraBundle"},{"text":"KnpUGuardBundle","link":"https://github.com/knpuniversity/KnpUGuardBundle"},{"text":"SamlBundle","link":"https://github.com/pdias/SamlBundle"},{"text":"two-factor-bundle","link":"https://github.com/scheb/two-factor-bundle"}]},{"text":"Validation","link":"#validation","contents":[{"text":"dms-filter-bundle","link":"https://github.com/rdohms/dms-filter-bundle"},{"text":"PasswordStrengthBundle","link":"https://github.com/jbafford/PasswordStrengthBundle"},{"text":"vatin-bundle","link":"https://github.com/ddeboer/vatin-bundle"}]},{"text":"Web Services","link":"#web-services","contents":[{"text":"api2symfony-bundle","link":"https://github.com/creads/api2symfony-bundle"},{"text":"BazingaHateoasBundle","link":"https://github.com/willdurand/BazingaHateoasBundle"},{"text":"DunglasAngularCsrfBundle","link":"https://github.com/dunglas/DunglasAngularCsrfBundle"},{"text":"DunglasApiBundle","link":"https://github.com/dunglas/DunglasApiBundle"},{"text":"FOSOAuthServerBundle","link":"https://github.com/FriendsOfSymfony/FOSOAuthServerBundle"},{"text":"FOSRestBundle","link":"https://github.com/FriendsOfSymfony/FOSRestBundle"},{"text":"JMDRestBundle","link":"https://github.com/mops1k/JMDRestBundle"},{"text":"JMSSerializerBundle","link":"https://github.com/schmittjoh/JMSSerializerBundle"},{"text":"JSONApiBundle","link":"https://github.com/nilportugues/symfony-jsonapi"},{"text":"KnpJsonSchemaBundle","link":"https://github.com/KnpLabs/KnpJsonSchemaBundle"},{"text":"LemonRestBundle","link":"https://github.com/stanlemon/rest-bundle"},{"text":"LexikJWTAuthenticationBundle","link":"https://github.com/lexik/LexikJWTAuthenticationBundle"},{"text":"NelmioApiDocBundle","link":"https://github.com/nelmio/NelmioApiDocBundle"},{"text":"NelmioCorsBundle","link":"https://github.com/nelmio/NelmioCorsBundle"},{"text":"RateLimitBundle","link":"https://github.com/jaytaph/RateLimitBundle"},{"text":"RequestLimitBundle","link":"https://github.com/zim32/Symfony2-RequestLimitBundle"},{"text":"ResourceBundle","link":"https://github.com/ProgrammingAreHard/ResourceBundle"},{"text":"SerializedResponseBundle","link":"https://github.com/Pulpmedia/SerializedResponseBundle"},{"text":"SRIORestUploadBundle","link":"https://github.com/sroze/SRIORestUploadBundle"}]}]